{
  "lastUpdated": "2026-03-27",
  "words": [
    {
      "word": "contingent",
      "pronunciation": "/k\u0259n\u02c8t\u026and\u0292\u0259nt/",
      "definition": "dependent on circumstances; possible but not certain",
      "lessonDate": "2026-03-21",
      "context": "AWL set 1",
      "interval": 2,
      "nextReviewDate": "2026-03-26",
      "streak": 1,
      "timesQuizzed": 1,
      "timesCorrect": 1,
      "lastQuizzed": "2026-03-22"
    },
    {
      "word": "elicit",
      "pronunciation": "/\u026a\u02c8l\u026as\u026at/",
      "definition": "to draw out or evoke a response",
      "lessonDate": "2026-03-21",
      "context": "AWL set 1",
      "interval": 2,
      "nextReviewDate": "2026-03-26",
      "streak": 1,
      "timesQuizzed": 1,
      "timesCorrect": 1,
      "lastQuizzed": "2026-03-22"
    },
    {
      "word": "tentative",
      "pronunciation": "/\u02c8t\u025bnt\u0259t\u026av/",
      "definition": "not definite or certain; provisional",
      "lessonDate": "2026-03-21",
      "context": "AWL set 1",
      "interval": 2,
      "nextReviewDate": "2026-03-26",
      "streak": 1,
      "timesQuizzed": 1,
      "timesCorrect": 1,
      "lastQuizzed": "2026-03-22"
    },
    {
      "word": "pervasive",
      "pronunciation": "/p\u0259r\u02c8ve\u026as\u026av/",
      "definition": "spreading widely throughout an area or group",
      "lessonDate": "2026-03-21",
      "context": "AWL set 1",
      "interval": 2,
      "nextReviewDate": "2026-03-26",
      "streak": 1,
      "timesQuizzed": 1,
      "timesCorrect": 1,
      "lastQuizzed": "2026-03-22"
    },
    {
      "word": "mitigate",
      "pronunciation": "/\u02c8m\u026at\u026a\u0261e\u026at/",
      "definition": "to reduce the severity or impact of something negative",
      "lessonDate": "2026-03-21",
      "context": "AWL set 1 -- collocation note: collocates with risks/damage/effects, not wounds",
      "interval": 2,
      "nextReviewDate": "2026-03-26",
      "streak": 1,
      "timesQuizzed": 1,
      "timesCorrect": 1,
      "lastQuizzed": "2026-03-22"
    },
    {
      "word": "surprising",
      "pronunciation": "/s\u0259r\u02c8pra\u026az\u026a\u014b/",
      "definition": "causing surprise; unexpected",
      "lessonDate": "2026-03-22",
      "context": "Week 2 test -- spelling error: wrote suprising",
      "interval": 1,
      "nextReviewDate": "2026-03-27",
      "streak": 0,
      "timesQuizzed": 3,
      "timesCorrect": 0,
      "lastQuizzed": "2026-03-26"
    },
    {
      "word": "exhausted",
      "pronunciation": "/\u026a\u0261\u02c8z\u0254\u02d0st\u026ad/",
      "definition": "extremely tired; drained of energy",
      "lessonDate": "2026-03-22",
      "context": "Week 2 test",
      "interval": 2,
      "nextReviewDate": "2026-03-26",
      "streak": 1,
      "timesQuizzed": 1,
      "timesCorrect": 1,
      "lastQuizzed": "2026-03-22"
    },
    {
      "word": "boring",
      "pronunciation": "/\u02c8b\u0254\u02d0r\u026a\u014b/",
      "definition": "causing lack of interest; tedious (causes boredom in others)",
      "lessonDate": "2026-03-22",
      "context": "Week 2 test -- Q3 skipped",
      "interval": 1,
      "nextReviewDate": "2026-03-27",
      "streak": 0,
      "timesQuizzed": 3,
      "timesCorrect": 0,
      "lastQuizzed": "2026-03-26"
    },
    {
      "word": "scrutinize",
      "pronunciation": "/\u02c8skru\u02d0t\u026ana\u026az/",
      "definition": "to examine carefully and critically",
      "lessonDate": "2026-03-23",
      "context": "AWL set 2 -- used correctly in WhatsApp paragraph",
      "interval": 1,
      "nextReviewDate": "2026-03-27",
      "streak": 0,
      "timesQuizzed": 2,
      "timesCorrect": 0,
      "lastQuizzed": "2026-03-26"
    },
    {
      "word": "prevalent",
      "pronunciation": "/\u02c8pr\u025bv\u0259l\u0259nt/",
      "definition": "widespread; common across a context or population",
      "lessonDate": "2026-03-23",
      "context": "AWL set 2 -- collocation note: not for local/specific datasets",
      "interval": 1,
      "nextReviewDate": "2026-03-27",
      "streak": 0,
      "timesQuizzed": 2,
      "timesCorrect": 0,
      "lastQuizzed": "2026-03-26"
    },
    {
      "word": "articulate",
      "pronunciation": "/\u0251\u02d0r\u02c8t\u026akj\u028ale\u026at/",
      "definition": "to express thoughts clearly and effectively (v.); able to express clearly (adj.)",
      "lessonDate": "2026-03-23",
      "context": "AWL set 2",
      "interval": 1,
      "nextReviewDate": "2026-03-27",
      "streak": 0,
      "timesQuizzed": 2,
      "timesCorrect": 0,
      "lastQuizzed": "2026-03-26"
    },
    {
      "word": "ambiguous",
      "pronunciation": "/\u00e6m\u02c8b\u026a\u0261ju\u0259s/",
      "definition": "open to more than one interpretation; unclear",
      "lessonDate": "2026-03-23",
      "context": "AWL set 2",
      "interval": 1,
      "nextReviewDate": "2026-03-24",
      "streak": 0,
      "timesQuizzed": 0,
      "timesCorrect": 0,
      "lastQuizzed": null
    },
    {
      "word": "substantiate",
      "pronunciation": "/s\u0259b\u02c8st\u00e6n\u0283ie\u026at/",
      "definition": "to provide evidence that supports a claim",
      "lessonDate": "2026-03-23",
      "context": "AWL set 2",
      "interval": 1,
      "nextReviewDate": "2026-03-25",
      "streak": 0,
      "timesQuizzed": 0,
      "timesCorrect": 0,
      "lastQuizzed": null
    },
    {
      "word": "coherent",
      "pronunciation": "/ko\u028a\u02c8h\u026a\u0259r\u0259nt/",
      "definition": "logically consistent and clearly connected; forming a unified whole",
      "lessonDate": "2026-03-24",
      "context": "AWL set 3",
      "interval": 1,
      "nextReviewDate": "2026-03-25",
      "streak": 0,
      "timesQuizzed": 0,
      "timesCorrect": 0,
      "lastQuizzed": null
    },
    {
      "word": "implicit",
      "pronunciation": "/\u026am\u02c8pl\u026as\u026at/",
      "definition": "implied or understood without being directly stated",
      "lessonDate": "2026-03-24",
      "context": "AWL set 3",
      "interval": 1,
      "nextReviewDate": "2026-03-25",
      "streak": 0,
      "timesQuizzed": 0,
      "timesCorrect": 0,
      "lastQuizzed": null
    },
    {
      "word": "derive",
      "pronunciation": "/d\u026a\u02c8ra\u026av/",
      "definition": "to develop or obtain from a source; to have as an origin",
      "lessonDate": "2026-03-24",
      "context": "AWL set 3",
      "interval": 1,
      "nextReviewDate": "2026-03-25",
      "streak": 0,
      "timesQuizzed": 0,
      "timesCorrect": 0,
      "lastQuizzed": null
    },
    {
      "word": "constitute",
      "pronunciation": "/\u02c8k\u0252nst\u026atju\u02d0t/",
      "definition": "to form or make up; to be considered as",
      "lessonDate": "2026-03-24",
      "context": "AWL set 3",
      "interval": 1,
      "nextReviewDate": "2026-03-25",
      "streak": 0,
      "timesQuizzed": 0,
      "timesCorrect": 0,
      "lastQuizzed": null
    },
    {
      "word": "dimension",
      "pronunciation": "/da\u026a\u02c8m\u025bn\u0283\u0259n/",
      "definition": "an aspect or feature of a situation; a scale of measurement",
      "lessonDate": "2026-03-24",
      "context": "AWL set 3",
      "interval": 1,
      "nextReviewDate": "2026-03-25",
      "streak": 0,
      "timesQuizzed": 0,
      "timesCorrect": 0,
      "lastQuizzed": null
    },
    {
      "word": "inherent",
      "pronunciation": "/\u026an\u02c8h\u026a\u0259r\u0259nt/",
      "definition": "naturally built in; existing as an essential part of something",
      "lessonDate": "2026-03-25",
      "context": "AWL set 4",
      "interval": 1,
      "nextReviewDate": "2026-03-26",
      "streak": 0,
      "timesQuizzed": 0,
      "timesCorrect": 0,
      "lastQuizzed": null
    },
    {
      "word": "facilitate",
      "pronunciation": "/f\u0259\u02c8s\u026al\u026ate\u026at/",
      "definition": "to make a process easier or possible",
      "lessonDate": "2026-03-25",
      "context": "AWL set 4",
      "interval": 1,
      "nextReviewDate": "2026-03-26",
      "streak": 0,
      "timesQuizzed": 0,
      "timesCorrect": 0,
      "lastQuizzed": null
    },
    {
      "word": "acknowledge",
      "pronunciation": "/\u0259k\u02c8n\u0252l\u026ad\u0292/",
      "definition": "to recognize or accept the existence or truth of something",
      "lessonDate": "2026-03-25",
      "context": "AWL set 4",
      "interval": 1,
      "nextReviewDate": "2026-03-26",
      "streak": 0,
      "timesQuizzed": 0,
      "timesCorrect": 0,
      "lastQuizzed": null
    },
    {
      "word": "prominent",
      "pronunciation": "/\u02c8pr\u0252m\u026an\u0259nt/",
      "definition": "important, well-known, or clearly standing out",
      "lessonDate": "2026-03-25",
      "context": "AWL set 4",
      "interval": 1,
      "nextReviewDate": "2026-03-26",
      "streak": 0,
      "timesQuizzed": 0,
      "timesCorrect": 0,
      "lastQuizzed": null
    },
    {
      "word": "sustain",
      "pronunciation": "/s\u0259\u02c8ste\u026an/",
      "definition": "to maintain something over time; to keep it going",
      "lessonDate": "2026-03-25",
      "context": "AWL set 4",
      "interval": 1,
      "nextReviewDate": "2026-03-26",
      "streak": 0,
      "timesQuizzed": 0,
      "timesCorrect": 0,
      "lastQuizzed": null
    },
    {
      "word": "comprise",
      "pronunciation": "/k\u0259m\u02c8pra\u026az/",
      "definition": "to consist of; to include as parts of a whole",
      "lessonDate": "2026-03-26",
      "context": "AWL set 5 -- note: do not use 'is comprised of'; use 'comprises' or 'is composed of'",
      "interval": 1,
      "nextReviewDate": "2026-03-27",
      "streak": 0,
      "timesQuizzed": 0,
      "timesCorrect": 0,
      "lastQuizzed": null
    },
    {
      "word": "generate",
      "pronunciation": "/\u02c8d\u0292\u025bn\u0259re\u026at/",
      "definition": "to produce or create something",
      "lessonDate": "2026-03-26",
      "context": "AWL set 5",
      "interval": 1,
      "nextReviewDate": "2026-03-27",
      "streak": 0,
      "timesQuizzed": 0,
      "timesCorrect": 0,
      "lastQuizzed": null
    },
    {
      "word": "integrate",
      "pronunciation": "/\u02c8\u026ant\u026a\u0261re\u026at/",
      "definition": "to combine elements into a unified whole",
      "lessonDate": "2026-03-26",
      "context": "AWL set 5",
      "interval": 1,
      "nextReviewDate": "2026-03-27",
      "streak": 0,
      "timesQuizzed": 0,
      "timesCorrect": 0,
      "lastQuizzed": null
    },
    {
      "word": "attribute",
      "pronunciation": "/\u02c8\u00e6tr\u026abju\u02d0t/ (n) /\u0259\u02c8tr\u026abju\u02d0t/ (v)",
      "definition": "(n) a quality or defining feature; (v) to credit something to a source",
      "lessonDate": "2026-03-26",
      "context": "AWL set 5 -- note: pronunciation changes between noun and verb",
      "interval": 1,
      "nextReviewDate": "2026-03-27",
      "streak": 0,
      "timesQuizzed": 0,
      "timesCorrect": 0,
      "lastQuizzed": null
    },
    {
      "word": "framework",
      "pronunciation": "/\u02c8fre\u026amw\u025c\u02d0k/",
      "definition": "a conceptual structure or system of ideas",
      "lessonDate": "2026-03-26",
      "context": "AWL set 5",
      "interval": 1,
      "nextReviewDate": "2026-03-27",
      "streak": 0,
      "timesQuizzed": 0,
      "timesCorrect": 0,
      "lastQuizzed": null
    },
    {
      "word": "empirical",
      "pronunciation": "/\u026am\u02c8p\u026ar\u026ak\u0259l/",
      "definition": "based on observation or experience, not theory alone",
      "lessonDate": "2026-03-27",
      "context": "The study draws on empirical evidence from three field sites.",
      "interval": 1,
      "nextReviewDate": "2026-03-28",
      "streak": 0,
      "timesQuizzed": 0,
      "timesCorrect": 0,
      "lastQuizzed": null
    },
    {
      "word": "paradigm",
      "pronunciation": "/\u02c8p\u00e6r\u0259da\u026am/",
      "definition": "a dominant model or framework that shapes how a field thinks",
      "lessonDate": "2026-03-27",
      "context": "The shift from object to process represents a new paradigm in curatorial practice.",
      "interval": 1,
      "nextReviewDate": "2026-03-28",
      "streak": 0,
      "timesQuizzed": 0,
      "timesCorrect": 0,
      "lastQuizzed": null
    },
    {
      "word": "inhibit",
      "pronunciation": "/\u026an\u02c8h\u026ab\u026at/",
      "definition": "to hinder, slow, or prevent",
      "lessonDate": "2026-03-27",
      "context": "Rigid assessment criteria can inhibit creative risk-taking.",
      "interval": 1,
      "nextReviewDate": "2026-03-28",
      "streak": 0,
      "timesQuizzed": 0,
      "timesCorrect": 0,
      "lastQuizzed": null
    },
    {
      "word": "concurrent",
      "pronunciation": "/k\u0259n\u02c8k\u025c\u02d0r\u0259nt/",
      "definition": "existing or happening at the same time",
      "lessonDate": "2026-03-27",
      "context": "The two exhibitions ran concurrently and shared a common critical framework.",
      "interval": 1,
      "nextReviewDate": "2026-03-28",
      "streak": 0,
      "timesQuizzed": 0,
      "timesCorrect": 0,
      "lastQuizzed": null
    },
    {
      "word": "mediate",
      "pronunciation": "/\u02c8mi\u02d0die\u026at/",
      "definition": "to intervene between parties; to act as a channel or transmit",
      "lessonDate": "2026-03-27",
      "context": "Digital tools mediate the relationship between the artist and the audience.",
      "interval": 1,
      "nextReviewDate": "2026-03-28",
      "streak": 0,
      "timesQuizzed": 0,
      "timesCorrect": 0,
      "lastQuizzed": null
    }
  ],
  "graduated": [],
  "quizHistory": [
    {
      "date": "2026-03-22",
      "words": [
        "contingent",
        "elicit",
        "tentative",
        "pervasive",
        "mitigate",
        "surprising",
        "exhausted",
        "boring"
      ],
      "results": {
        "contingent": true,
        "elicit": true,
        "tentative": true,
        "pervasive": true,
        "mitigate": true,
        "surprising": false,
        "exhausted": true,
        "boring": false
      }
    },
    {
      "date": "2026-03-24",
      "words": [
        "surprising",
        "boring",
        "scrutinize",
        "articulate",
        "ambiguous"
      ],
      "results": {}
    },
    {
      "date": "2026-03-25",
      "words": [
        "surprising",
        "boring",
        "scrutinize",
        "prevalent",
        "articulate"
      ],
      "results": null,
      "note": "results pending \u2014 check next session"
    },
    {
      "date": "2026-03-26",
      "words": [
        "surprising",
        "boring",
        "scrutinize",
        "prevalent",
        "articulate"
      ],
      "results": null,
      "note": "results pending -- check next session"
    }
  ]
}